audio/__init__.py
audio/tts.py
image/__init__.py
image/sh.py
text/__init__.py
text/gpt_new.py
neyro_api-0.1.8.dist-info/LICENSE
neyro_api-0.1.8.dist-info/METADATA
neyro_api-0.1.8.dist-info/WHEEL
neyro_api-0.1.8.dist-info/top_level.txt
neyro_api-0.1.8.dist-info/RECORD
