Metadata-Version: 2.1
Name: neyro-api
Version: 0.1.8
Summary: A Python library for interacting with the Neyro API
Author: Chelik23, the-mw-dev
Author-email: workghmail5775@gmail.com
Classifier: Programming Language :: Python :: 3
Classifier: License :: OSI Approved :: MIT License
Classifier: Operating System :: OS Independent
Requires-Python: >=3.9
License-File: LICENSE
Requires-Dist: httpx
